inmanta_plugins/fs/__init__.py
inmanta_plugins/fs/json_file.py
inmanta_plugins/fs/resources.py
inmanta_plugins/fs/setup.cfg
inmanta_plugins/fs/files/.gitkeep
inmanta_plugins/fs/model/_init.cf
inmanta_plugins/fs/templates/.gitkeep
inmanta_module_fs-1.1.1.dist-info/METADATA
inmanta_module_fs-1.1.1.dist-info/WHEEL
inmanta_module_fs-1.1.1.dist-info/top_level.txt
inmanta_module_fs-1.1.1.dist-info/RECORD
